TushareDownloader/__init__.py
TushareDownloader/database.py
TushareDownloader/query.py
TushareDownloader/save_and_log.py
TushareDownloader/tushare_api.py
TushareDownloader/tushare_downloader.py
TushareDownloader-1.0.0.dist-info/LICENSE
TushareDownloader-1.0.0.dist-info/METADATA
TushareDownloader-1.0.0.dist-info/WHEEL
TushareDownloader-1.0.0.dist-info/top_level.txt
TushareDownloader-1.0.0.dist-info/RECORD
